paddleocr_mcp/__init__.py
paddleocr_mcp/__main__.py
paddleocr_mcp/pipelines.py
paddleocr_mcp/py.typed
iflow_mcp_paddleocr_mcp-0.2.0.dist-info/METADATA
iflow_mcp_paddleocr_mcp-0.2.0.dist-info/WHEEL
iflow_mcp_paddleocr_mcp-0.2.0.dist-info/entry_points.txt
iflow_mcp_paddleocr_mcp-0.2.0.dist-info/top_level.txt
iflow_mcp_paddleocr_mcp-0.2.0.dist-info/RECORD
